PySysrev/__init__.py
PySysrev/funcs.py
PySysrev-1.2.1.dist-info/METADATA
PySysrev-1.2.1.dist-info/WHEEL
PySysrev-1.2.1.dist-info/top_level.txt
PySysrev-1.2.1.dist-info/RECORD
