Metadata-Version: 2.1
Name: PySysrev
Version: 1.2.1
Summary: Gets annotations from Sysrev API
Home-page: https://github.com/sysrev/PySysrev
Author: nole-lin
Author-email: nole@insilica.co
License: UNKNOWN
Platform: UNKNOWN
Requires-Python: >=3.6
Requires-Dist: pandas
Requires-Dist: requests
Requires-Dist: pathlib
